graceful_shutdown/__init__.py
graceful_shutdown/manager.py
graceful_shutdown-0.1.2.dist-info/METADATA
graceful_shutdown-0.1.2.dist-info/WHEEL
graceful_shutdown-0.1.2.dist-info/top_level.txt
graceful_shutdown-0.1.2.dist-info/RECORD
