Metadata-Version: 2.1
Name: graceful-shutdown
Version: 0.1.2
Summary: Graceful shutdown solution for Python
Home-page: https://github.com/turnbullerin/graceful-shutdown
Author: Erin Turnbull
Author-email: erin.a.turnbull@gmail.com
Project-URL: Bug Tracker, https://github.com/turnbullerin/graceful-shutdown/issues
Classifier: Programming Language :: Python :: 3
Classifier: License :: OSI Approved :: MIT License
Classifier: Operating System :: OS Independent
Requires-Python: >=3.6
Requires-Dist: autoinject (>=0.2.2)
Requires-Dist: pywin32 ; os_name == "nt"
